peg_leg/__init__.py
peg_leg/ast.py
peg_leg/parser.py
peg_leg/peg.py
peg_leg-0.4.0.dist-info/LICENSE
peg_leg-0.4.0.dist-info/METADATA
peg_leg-0.4.0.dist-info/WHEEL
peg_leg-0.4.0.dist-info/top_level.txt
peg_leg-0.4.0.dist-info/RECORD
