Metadata-Version: 2.1
Name: peg-leg
Version: 0.4.0
Summary: PEG parser generator
Home-page: https://github.com/formerly-a-trickster/peg-leg
Author: Gabriel Ionescu
Author-email: gabe@erisian.tech
License: UNKNOWN
Platform: UNKNOWN
Classifier: Programming Language :: Python :: 3
Classifier: Operating System :: OS Independent
Requires-Python: >=3.6
